wilcox_utility_functions/__init__.py
wilcox_utility_functions/calcs.py
wilcox_utility_functions/print_input.py
wilcox_utility_functions-0.0.4.dist-info/METADATA
wilcox_utility_functions-0.0.4.dist-info/WHEEL
wilcox_utility_functions-0.0.4.dist-info/top_level.txt
wilcox_utility_functions-0.0.4.dist-info/RECORD
